MANIFEST.in
README.md
jenkins.sh
requirement.txt
setup.py
tokenleader/__init__.py
tokenleader/app.py
tokenleader/app_run.py
tokenleader.egg-info/PKG-INFO
tokenleader.egg-info/SOURCES.txt
tokenleader.egg-info/dependency_links.txt
tokenleader.egg-info/entry_points.txt
tokenleader.egg-info/not-zip-safe
tokenleader.egg-info/requires.txt
tokenleader.egg-info/top_level.txt
tokenleader/app1/__init__.py
tokenleader/app1/adminops/__init__.py
tokenleader/app1/adminops/admin_cli_parser.py
tokenleader/app1/adminops/admin_functions.py
tokenleader/app1/adminops/adminops_restapi.py
tokenleader/app1/adminops/base_ops.py
tokenleader/app1/authentication/__init__.py
tokenleader/app1/authentication/models.py
tokenleader/app1/authentication/token_after_login.py
tokenleader/app1/catalog/__init__.py
tokenleader/app1/catalog/catalog_functions.py
tokenleader/app1/catalog/models_catalog.py
tokenleader/app1/configs/__init__.py
tokenleader/app1/configs/configs.py
tokenleader/app1/configs/settings.ini
tokenleader/app1/configs/testconfigs.py
tokenleader/migrations/README
tokenleader/migrations/__init__.py
tokenleader/migrations/alembic.ini
tokenleader/migrations/env.py
tokenleader/migrations/script.py.mako
tokenleader/migrations/versions/3f6c8ac80cdf_.py
tokenleader/migrations/versions/__init__.py
tokenleader/tests/__init__.py
tokenleader/tests/base_test.py
tokenleader/tests/test_admin_ops.py
tokenleader/tests/test_admin_restapi.py
tokenleader/tests/test_auth.py
tokenleader/tests/test_catalog_ops.py