Metadata-Version: 1.0
Name: tokenleader
Version: 1.8
Summary: tokenleader server can be used by other microservices for token based  authentication and authorization
Home-page: https://github.com/microservice-tsp-billing/tokenleader
Author: Bhujay Kumar Bhatta
Author-email: bhujay.bhatta@yahoo.com
License: Apache Software License
Platform: UNKNOWN
